mrack/__init__.py
mrack/config.py
mrack/context.py
mrack/errors.py
mrack/host.py
mrack/run.py
mrack/utils.py
mrack/version.py
mrack/actions/__init__.py
mrack/actions/action.py
mrack/actions/destroy.py
mrack/actions/etchosts.py
mrack/actions/list.py
mrack/actions/output.py
mrack/actions/ssh.py
mrack/actions/up.py
mrack/data/mrack.conf
mrack/data/provisioning-config.yaml
mrack/data/seccomp.json
mrack/dbdrivers/__init__.py
mrack/dbdrivers/file.py
mrack/outputs/__init__.py
mrack/outputs/ansible_inventory.py
mrack/outputs/pytest_mh.py
mrack/outputs/pytest_multihost.py
mrack/outputs/utils.py
mrack/providers/__init__.py
mrack/providers/aws.py
mrack/providers/beaker.py
mrack/providers/openstack.py
mrack/providers/podman.py
mrack/providers/provider.py
mrack/providers/static.py
mrack/providers/virt.py
mrack/providers/utils/__init__.py
mrack/providers/utils/osapi.py
mrack/providers/utils/podman.py
mrack/providers/utils/testcloud.py
mrack/transformers/__init__.py
mrack/transformers/aws.py
mrack/transformers/beaker.py
mrack/transformers/openstack.py
mrack/transformers/podman.py
mrack/transformers/static.py
mrack/transformers/transformer.py
mrack/transformers/virt.py
mrack-1.25.0.data/scripts/mrack
mrack-1.25.0.dist-info/licenses/LICENSE
mrack-1.25.0.dist-info/METADATA
mrack-1.25.0.dist-info/WHEEL
mrack-1.25.0.dist-info/top_level.txt
mrack-1.25.0.dist-info/RECORD
