Metadata-Version: 2.4
Name: mrack
Version: 1.25.0
Summary: Multicloud use-case based multihost async provisioner for CIs and testing during development
Home-page: https://github.com/neoave/mrack
Author: Petr Vobornik
Maintainer: Red Hat IdM-Ops team
Maintainer-email: idmops@redhat.com
License: Apache License 2.0
License-File: LICENSE
Requires-Dist: beaker-client>=29.2
Requires-Dist: botocore>=1.14.17
Requires-Dist: boto3>=1.11.17
Requires-Dist: click>=7.0.0
Requires-Dist: pyyaml>=5.0.0
Requires-Dist: asyncopenstackclient>=0.9.0
Requires-Dist: testcloud>=0.5.0
Requires-Dist: aiofiles>=23.1.0
Requires-Dist: os_client_config>=2.1.0
Requires-Dist: async_timeout~=4.0.3
Provides-Extra: krb-owner
Requires-Dist: gssapi; extra == "krb-owner"
Dynamic: author
Dynamic: description
Dynamic: description-content-type
Dynamic: home-page
Dynamic: license
Dynamic: license-file
Dynamic: maintainer
Dynamic: maintainer-email
Dynamic: provides-extra
Dynamic: requires-dist
Dynamic: summary
